{"at_gateway":0,"at_vmm":2689127600471,"arrived":2689127720641,"allocated":2689127915935,"launched":2689127917429,"completed":2689618320760,"request":{"function":"grades","payload":{"args":{"test_results":"github/cos316/example//b541c851d79edad1d05fc64c1bcca88800703a30/test_results.jsonl"},"context":{"commit":"b541c851d79edad1d05fc64c1bcca88800703a30","metadata":{"assignment":"example","trial":0},"push_date":1642798607,"repository":"cos316/example/"},"workflow":["generate_report","graderbot_post_process"]}}}
{"at_gateway":0,"at_vmm":2733995017774,"arrived":2733995156512,"allocated":2733995310551,"launched":2733995311714,"completed":2734486817716,"request":{"function":"grades","payload":{"args":{"test_results":"github/cos316/example//b541c851d79edad1d05fc64c1bcca88800703a30/test_results.jsonl"},"context":{"commit":"b541c851d79edad1d05fc64c1bcca88800703a30","metadata":{"assignment":"example","trial":2},"push_date":1642798607,"repository":"cos316/example/"},"workflow":["generate_report","graderbot_post_process"]}}}
{"at_gateway":0,"at_vmm":2778822348244,"arrived":2778822505771,"allocated":2778822658742,"launched":2778822659894,"completed":2779314587443,"request":{"function":"grades","payload":{"args":{"test_results":"github/cos316/example//b541c851d79edad1d05fc64c1bcca88800703a30/test_results.jsonl"},"context":{"commit":"b541c851d79edad1d05fc64c1bcca88800703a30","metadata":{"assignment":"example","trial":4},"push_date":1642798607,"repository":"cos316/example/"},"workflow":["generate_report","graderbot_post_process"]}}}
{"at_gateway":0,"at_vmm":2823799130743,"arrived":2823799216315,"allocated":2823799360170,"launched":2823799361363,"completed":2824290635093,"request":{"function":"grades","payload":{"args":{"test_results":"github/cos316/example//b541c851d79edad1d05fc64c1bcca88800703a30/test_results.jsonl"},"context":{"commit":"b541c851d79edad1d05fc64c1bcca88800703a30","metadata":{"assignment":"example","trial":6},"push_date":1642798607,"repository":"cos316/example/"},"workflow":["generate_report","graderbot_post_process"]}}}
{"at_gateway":0,"at_vmm":2868822209916,"arrived":2868822323719,"allocated":2868822513125,"launched":2868822514358,"completed":2869310650718,"request":{"function":"grades","payload":{"args":{"test_results":"github/cos316/example//b541c851d79edad1d05fc64c1bcca88800703a30/test_results.jsonl"},"context":{"commit":"b541c851d79edad1d05fc64c1bcca88800703a30","metadata":{"assignment":"example","trial":8},"push_date":1642798607,"repository":"cos316/example/"},"workflow":["generate_report","graderbot_post_process"]}}}
{"at_gateway":0,"at_vmm":2913831471767,"arrived":2913831617150,"allocated":2913831767570,"launched":2913831768843,"completed":2914322546629,"request":{"function":"grades","payload":{"args":{"test_results":"github/cos316/example//b541c851d79edad1d05fc64c1bcca88800703a30/test_results.jsonl"},"context":{"commit":"b541c851d79edad1d05fc64c1bcca88800703a30","metadata":{"assignment":"example","trial":10},"push_date":1642798607,"repository":"cos316/example/"},"workflow":["generate_report","graderbot_post_process"]}}}
{"at_gateway":0,"at_vmm":2958822446161,"arrived":2958822583751,"allocated":2958822783331,"launched":2958822784519,"completed":2959314453694,"request":{"function":"grades","payload":{"args":{"test_results":"github/cos316/example//b541c851d79edad1d05fc64c1bcca88800703a30/test_results.jsonl"},"context":{"commit":"b541c851d79edad1d05fc64c1bcca88800703a30","metadata":{"assignment":"example","trial":12},"push_date":1642798607,"repository":"cos316/example/"},"workflow":["generate_report","graderbot_post_process"]}}}
{"at_gateway":0,"at_vmm":3003823032890,"arrived":3003823170856,"allocated":3003823358012,"launched":3003823359260,"completed":3004314439085,"request":{"function":"grades","payload":{"args":{"test_results":"github/cos316/example//b541c851d79edad1d05fc64c1bcca88800703a30/test_results.jsonl"},"context":{"commit":"b541c851d79edad1d05fc64c1bcca88800703a30","metadata":{"assignment":"example","trial":14},"push_date":1642798607,"repository":"cos316/example/"},"workflow":["generate_report","graderbot_post_process"]}}}
{"at_gateway":0,"at_vmm":3048847030086,"arrived":3048847139521,"allocated":3048847337792,"launched":3048847339230,"completed":3049338741456,"request":{"function":"grades","payload":{"args":{"test_results":"github/cos316/example//b541c851d79edad1d05fc64c1bcca88800703a30/test_results.jsonl"},"context":{"commit":"b541c851d79edad1d05fc64c1bcca88800703a30","metadata":{"assignment":"example","trial":16},"push_date":1642798607,"repository":"cos316/example/"},"workflow":["generate_report","graderbot_post_process"]}}}
{"at_gateway":0,"at_vmm":3094037290215,"arrived":3094037372498,"allocated":3094037582206,"launched":3094037583860,"completed":3094526585958,"request":{"function":"grades","payload":{"args":{"test_results":"github/cos316/example//b541c851d79edad1d05fc64c1bcca88800703a30/test_results.jsonl"},"context":{"commit":"b541c851d79edad1d05fc64c1bcca88800703a30","metadata":{"assignment":"example","trial":18},"push_date":1642798607,"repository":"cos316/example/"},"workflow":["generate_report","graderbot_post_process"]}}}
{"at_gateway":0,"at_vmm":3138899151883,"arrived":3138899264976,"allocated":3138899476799,"launched":3138899477927,"completed":3139390678154,"request":{"function":"grades","payload":{"args":{"test_results":"github/cos316/example//b541c851d79edad1d05fc64c1bcca88800703a30/test_results.jsonl"},"context":{"commit":"b541c851d79edad1d05fc64c1bcca88800703a30","metadata":{"assignment":"example","trial":20},"push_date":1642798607,"repository":"cos316/example/"},"workflow":["generate_report","graderbot_post_process"]}}}
{"at_gateway":0,"at_vmm":3183777624588,"arrived":3183777752085,"allocated":3183777958119,"launched":3183777959297,"completed":3184266689017,"request":{"function":"grades","payload":{"args":{"test_results":"github/cos316/example//b541c851d79edad1d05fc64c1bcca88800703a30/test_results.jsonl"},"context":{"commit":"b541c851d79edad1d05fc64c1bcca88800703a30","metadata":{"assignment":"example","trial":22},"push_date":1642798607,"repository":"cos316/example/"},"workflow":["generate_report","graderbot_post_process"]}}}
{"at_gateway":0,"at_vmm":3228763411985,"arrived":3228763539915,"allocated":3228763741815,"launched":3228763742887,"completed":3229254681840,"request":{"function":"grades","payload":{"args":{"test_results":"github/cos316/example//b541c851d79edad1d05fc64c1bcca88800703a30/test_results.jsonl"},"context":{"commit":"b541c851d79edad1d05fc64c1bcca88800703a30","metadata":{"assignment":"example","trial":24},"push_date":1642798607,"repository":"cos316/example/"},"workflow":["generate_report","graderbot_post_process"]}}}
{"at_gateway":0,"at_vmm":3274023075542,"arrived":3274023213062,"allocated":3274023379450,"launched":3274023380737,"completed":3274470617749,"request":{"function":"grades","payload":{"args":{"test_results":"github/cos316/example//b541c851d79edad1d05fc64c1bcca88800703a30/test_results.jsonl"},"context":{"commit":"b541c851d79edad1d05fc64c1bcca88800703a30","metadata":{"assignment":"example","trial":26},"push_date":1642798607,"repository":"cos316/example/"},"workflow":["generate_report","graderbot_post_process"]}}}
{"at_gateway":0,"at_vmm":3318818475585,"arrived":3318818579873,"allocated":3318818790222,"launched":3318818791325,"completed":3319266263783,"request":{"function":"grades","payload":{"args":{"test_results":"github/cos316/example//b541c851d79edad1d05fc64c1bcca88800703a30/test_results.jsonl"},"context":{"commit":"b541c851d79edad1d05fc64c1bcca88800703a30","metadata":{"assignment":"example","trial":28},"push_date":1642798607,"repository":"cos316/example/"},"workflow":["generate_report","graderbot_post_process"]}}}
{"at_gateway":0,"at_vmm":3363874721799,"arrived":3363874860637,"allocated":3363875031064,"launched":3363875032256,"completed":3364362853041,"request":{"function":"grades","payload":{"args":{"test_results":"github/cos316/example//b541c851d79edad1d05fc64c1bcca88800703a30/test_results.jsonl"},"context":{"commit":"b541c851d79edad1d05fc64c1bcca88800703a30","metadata":{"assignment":"example","trial":30},"push_date":1642798607,"repository":"cos316/example/"},"workflow":["generate_report","graderbot_post_process"]}}}
{"at_gateway":0,"at_vmm":3409141395160,"arrived":3409141533758,"allocated":3409141701799,"launched":3409141703212,"completed":3409630813949,"request":{"function":"grades","payload":{"args":{"test_results":"github/cos316/example//b541c851d79edad1d05fc64c1bcca88800703a30/test_results.jsonl"},"context":{"commit":"b541c851d79edad1d05fc64c1bcca88800703a30","metadata":{"assignment":"example","trial":32},"push_date":1642798607,"repository":"cos316/example/"},"workflow":["generate_report","graderbot_post_process"]}}}
{"at_gateway":0,"at_vmm":3454159474236,"arrived":3454159613545,"allocated":3454159752639,"launched":3454159753912,"completed":3454650662125,"request":{"function":"grades","payload":{"args":{"test_results":"github/cos316/example//b541c851d79edad1d05fc64c1bcca88800703a30/test_results.jsonl"},"context":{"commit":"b541c851d79edad1d05fc64c1bcca88800703a30","metadata":{"assignment":"example","trial":34},"push_date":1642798607,"repository":"cos316/example/"},"workflow":["generate_report","graderbot_post_process"]}}}
{"at_gateway":0,"at_vmm":3499077205836,"arrived":3499077347271,"allocated":3499077543171,"launched":3499077544434,"completed":3499566689472,"request":{"function":"grades","payload":{"args":{"test_results":"github/cos316/example//b541c851d79edad1d05fc64c1bcca88800703a30/test_results.jsonl"},"context":{"commit":"b541c851d79edad1d05fc64c1bcca88800703a30","metadata":{"assignment":"example","trial":36},"push_date":1642798607,"repository":"cos316/example/"},"workflow":["generate_report","graderbot_post_process"]}}}
{"at_gateway":0,"at_vmm":3544071871426,"arrived":3544071992593,"allocated":3544072146331,"launched":3544072147619,"completed":3544562585936,"request":{"function":"grades","payload":{"args":{"test_results":"github/cos316/example//b541c851d79edad1d05fc64c1bcca88800703a30/test_results.jsonl"},"context":{"commit":"b541c851d79edad1d05fc64c1bcca88800703a30","metadata":{"assignment":"example","trial":38},"push_date":1642798607,"repository":"cos316/example/"},"workflow":["generate_report","graderbot_post_process"]}}}
{"at_gateway":0,"at_vmm":3589059148783,"arrived":3589059277607,"allocated":3589059479247,"launched":3589059480485,"completed":3589550709981,"request":{"function":"grades","payload":{"args":{"test_results":"github/cos316/example//b541c851d79edad1d05fc64c1bcca88800703a30/test_results.jsonl"},"context":{"commit":"b541c851d79edad1d05fc64c1bcca88800703a30","metadata":{"assignment":"example","trial":40},"push_date":1642798607,"repository":"cos316/example/"},"workflow":["generate_report","graderbot_post_process"]}}}
{"at_gateway":0,"at_vmm":3634019170585,"arrived":3634019312195,"allocated":3634019501470,"launched":3634019503154,"completed":3634510723794,"request":{"function":"grades","payload":{"args":{"test_results":"github/cos316/example//b541c851d79edad1d05fc64c1bcca88800703a30/test_results.jsonl"},"context":{"commit":"b541c851d79edad1d05fc64c1bcca88800703a30","metadata":{"assignment":"example","trial":42},"push_date":1642798607,"repository":"cos316/example/"},"workflow":["generate_report","graderbot_post_process"]}}}
{"at_gateway":0,"at_vmm":3678884575214,"arrived":3678884687513,"allocated":3678884881460,"launched":3678884882668,"completed":3679374318688,"request":{"function":"grades","payload":{"args":{"test_results":"github/cos316/example//b541c851d79edad1d05fc64c1bcca88800703a30/test_results.jsonl"},"context":{"commit":"b541c851d79edad1d05fc64c1bcca88800703a30","metadata":{"assignment":"example","trial":44},"push_date":1642798607,"repository":"cos316/example/"},"workflow":["generate_report","graderbot_post_process"]}}}
{"at_gateway":0,"at_vmm":3724062224913,"arrived":3724062338714,"allocated":3724062447361,"launched":3724062448815,"completed":3724554363865,"request":{"function":"grades","payload":{"args":{"test_results":"github/cos316/example//b541c851d79edad1d05fc64c1bcca88800703a30/test_results.jsonl"},"context":{"commit":"b541c851d79edad1d05fc64c1bcca88800703a30","metadata":{"assignment":"example","trial":46},"push_date":1642798607,"repository":"cos316/example/"},"workflow":["generate_report","graderbot_post_process"]}}}
{"at_gateway":0,"at_vmm":3768980441020,"arrived":3768980564676,"allocated":3768980743985,"launched":3768980744964,"completed":3769466582655,"request":{"function":"grades","payload":{"args":{"test_results":"github/cos316/example//b541c851d79edad1d05fc64c1bcca88800703a30/test_results.jsonl"},"context":{"commit":"b541c851d79edad1d05fc64c1bcca88800703a30","metadata":{"assignment":"example","trial":48},"push_date":1642798607,"repository":"cos316/example/"},"workflow":["generate_report","graderbot_post_process"]}}}
